{"is_source_file": true, "format": "TypeScript (TSX)", "description": "This file defines a React functional component named NoteEditor, which provides a user interface for editing the title and content of a note. It handles state management for the note's fields, manages focus when the note changes, and provides callbacks for saving, deleting, or canceling edits. The component utilizes React hooks and TypeScript types for props and references.", "external_files": ["@/types/note"], "external_methods": [], "published": ["NoteEditor"], "classes": [], "methods": [{"name": "NoteEditor", "description": "React functional component for editing a note's title and content, with save, delete, and cancel actions."}], "calls": ["setTitle", "setContent", "React.useState", "React.useRef", "useEffect", "onSave", "onDelete", "onCancel"], "search-terms": ["NoteEditor", "React functional component", "note editing", "useRef", "useEffect", "typescript", "TSX", "notes_frontend/src/components/NoteEditor"], "state": 2, "file_id": 16, "knowledge_revision": 34, "git_revision": "", "ctags": [], "hash": "53874c722ceb55bdccbb7f1405d60181", "format-version": 4, "code-base-name": "notes_frontend", "filename": "notes_frontend/src/components/NoteEditor.tsx", "revision_history": [{"34": ""}]}